README.md
setup.py
pyjserver/__init__.py
pyjserver/__main__.py
pyjserver.egg-info/PKG-INFO
pyjserver.egg-info/SOURCES.txt
pyjserver.egg-info/dependency_links.txt
pyjserver.egg-info/top_level.txt
pyjserver/database/__init__.py
pyjserver/database/connector.py
pyjserver/database/data.py
pyjserver/endpoint/__init__.py
pyjserver/endpoint/endpoint.py
pyjserver/endpoint/errorhandler.py
pyjserver/endpoint/methods.py